pyqt_tooltip_widget/__init__.py
pyqt_tooltip_widget/toolTipWidget.py
pyqt_tooltip_widget-0.0.1.dist-info/LICENSE
pyqt_tooltip_widget-0.0.1.dist-info/METADATA
pyqt_tooltip_widget-0.0.1.dist-info/WHEEL
pyqt_tooltip_widget-0.0.1.dist-info/top_level.txt
pyqt_tooltip_widget-0.0.1.dist-info/RECORD
